{
  "name" : "dynamicWidget",
  "version": "0.0.5",  
  "title" : "Dynamic Widget",
  "description": "Plugin for JQuery-UI that will retrieve widgets via ajax",
  "author" : {
    "name" : "Michael Harris",
    "email" : "michaeldewayneharris@gmail.com"
  },
  "licenses" : [{
      "type" : "MIT",
      "url": "http://opensource.org/licenses/MIT"
    }
  ],
  "dependencies": {
      "jquery": ">=1.11",
      "jquery-ui": ">=1.11"
  },
  "bugs": "https://github.com/michaeldewayneharris/dynamicWidget/issues",
  "homepage": "https://github.com/michaeldewayneharris/dynamicWidget",
  "docs": "https://github.com/michaeldewayneharris/dynamicWidget"
}